modules/__init__.py
modules/database_manager.py
modules/expander.py
modules/generator.py
genWizard-0.0.3.dist-info/LICENSE.txt
genWizard-0.0.3.dist-info/METADATA
genWizard-0.0.3.dist-info/WHEEL
genWizard-0.0.3.dist-info/top_level.txt
genWizard-0.0.3.dist-info/RECORD
