Metadata-Version: 2.1
Name: genWizard
Version: 0.0.3
Summary: genWizard allows for versatile usage of openAI generation and prompting management.
Home-page: https://github.com/ykim336/genWizard
Author: Isaac Moon
Author-email: ykim336@ucr.com
License: MIT
Keywords: machine learning
Classifier: Development Status :: 3 - Alpha
Classifier: Intended Audience :: Developers
Classifier: License :: OSI Approved :: MIT License
Classifier: Programming Language :: Python :: 3
License-File: LICENSE.txt
Requires-Dist: openai
